MANIFEST.in
README
__init__.py
__pkginfo__.py
entities.py
hooks.py
schema.py
setup.py
cubicweb_drh.egg-info/PKG-INFO
cubicweb_drh.egg-info/SOURCES.txt
cubicweb_drh.egg-info/dependency_links.txt
cubicweb_drh.egg-info/requires.txt
cubicweb_drh.egg-info/top_level.txt
i18n/en.po
i18n/fr.po
migration/0.12.0_Any.py
migration/0.14.0_Any.py
migration/0.15.0_Any.py
migration/0.16.0_Any.py
migration/0.18.0_Any.py
migration/0.19.0_Any.py
migration/0.20.0_Any.py
migration/0.6.0_Any.py
migration/postcreate.py
test/test_drh.py
views/__init__.py
views/boxes.py
views/primary.py
views/startup.py