Metadata-Version: 1.0
Name: cubicweb-drh
Version: 0.20.0
Summary: recruitment application based on the CubicWeb framework
Home-page: http://www.cubicweb.org/project/cubicweb-drh
Author: Logilab
Author-email: contact@logilab.fr
License: LGPL
Platform: UNKNOWN
